wslwinreg2/__init__.py
wslwinreg2/common.py
wslwinreg2/cygwinapi.py
wslwinreg2/nullapi.py
wslwinreg2/wslapi.py
wslwinreg2/bin/backend-x32.exe
wslwinreg2/bin/backend-x64.exe
wslwinreg2-1.3.0.dist-info/LICENSE.txt
wslwinreg2-1.3.0.dist-info/METADATA
wslwinreg2-1.3.0.dist-info/WHEEL
wslwinreg2-1.3.0.dist-info/top_level.txt
wslwinreg2-1.3.0.dist-info/RECORD
